ipgn2tdm.py
ipgn2tdm-0.3.2.dist-info/entry_points.txt
ipgn2tdm-0.3.2.dist-info/LICENSE
ipgn2tdm-0.3.2.dist-info/WHEEL
ipgn2tdm-0.3.2.dist-info/METADATA
ipgn2tdm-0.3.2.dist-info/RECORD
