Metadata-Version: 2.1
Name: ipgn2tdm
Version: 0.3.2
Summary: Tableau de marche depuis gpx iPhiGéNie. 
Author-email: Philippe Makowski <pmakowski@espelida.com>
Requires-Python: >=3.9
Classifier: Intended Audience :: End Users/Desktop
Classifier: License :: OSI Approved :: BSD License
Classifier: Programming Language :: Python :: 3
Classifier: Development Status :: 5 - Production/Stable
Classifier: Natural Language :: French
Classifier: Topic :: Utilities
Requires-Dist: utm >= 0.7.0
Requires-Dist: python-docx >= 0.8.11
Requires-Dist: matplotlib
Requires-Dist: pytest ; extra == "test"
Project-URL: Home, https://gitlab.com/pmakowski/ipgn2tdm
Provides-Extra: test
